storck_client.py
storck_sync.py
storck_upload.py
storck_client-0.1.6.dist-info/METADATA
storck_client-0.1.6.dist-info/WHEEL
storck_client-0.1.6.dist-info/top_level.txt
storck_client-0.1.6.dist-info/RECORD
