Metadata-Version: 2.1
Name: storck-client
Version: 0.1.6
Summary: A client library for storck database system
Home-page: https://gitlab.cern.ch/velo-calibration-software/storck_client
Author-email: mmajewsk@cern.ch
Project-URL: Bug Tracker, https://gitlab.cern.ch/velo-calibration-software/storck_client/-/issues
Classifier: Programming Language :: Python :: 3
Classifier: Operating System :: OS Independent
Requires-Python: >=3.6
Requires-Dist: requests (>=2.25.1)
